LICENSE
nonebot_ark_record/.git/COMMIT_EDITMSG
nonebot_ark_record/.git/config
nonebot_ark_record/.git/description
nonebot_ark_record/.git/HEAD
nonebot_ark_record/.git/hooks/applypatch-msg.sample
nonebot_ark_record/.git/hooks/commit-msg.sample
nonebot_ark_record/.git/hooks/fsmonitor-watchman.sample
nonebot_ark_record/.git/hooks/post-update.sample
nonebot_ark_record/.git/hooks/pre-applypatch.sample
nonebot_ark_record/.git/hooks/pre-commit.sample
nonebot_ark_record/.git/hooks/pre-merge-commit.sample
nonebot_ark_record/.git/hooks/pre-push.sample
nonebot_ark_record/.git/hooks/pre-rebase.sample
nonebot_ark_record/.git/hooks/pre-receive.sample
nonebot_ark_record/.git/hooks/prepare-commit-msg.sample
nonebot_ark_record/.git/hooks/push-to-checkout.sample
nonebot_ark_record/.git/hooks/update.sample
nonebot_ark_record/.git/index
nonebot_ark_record/.git/info/exclude
nonebot_ark_record/.git/logs/HEAD
nonebot_ark_record/.git/logs/refs/heads/master
nonebot_ark_record/.git/objects/02/a3cbe7a2c4a52d1719789d0ae8823e3958651c
nonebot_ark_record/.git/objects/03/c84d7402baac2814f1ec8019df73c6668acf46
nonebot_ark_record/.git/objects/04/00a6e7c7eb9c18cb9f4b54fde85cb254fcfe91
nonebot_ark_record/.git/objects/04/96580373a747b66334f9baf3e72e85c3e664e7
nonebot_ark_record/.git/objects/05/2b98a476764d4dbd6d185d23fe8dfcc9f32a1b
nonebot_ark_record/.git/objects/05/6c2d1438a9607b849e80e15e9abc3bb82a2b9c
nonebot_ark_record/.git/objects/05/967ae706e37d5aa0a1cd355a3bba6a0c4717a0
nonebot_ark_record/.git/objects/06/7cc12a41db2d0540bb03ca449b436dcda1b58f
nonebot_ark_record/.git/objects/07/7d345db4df4faf53fa0a5fbc919a256654d286
nonebot_ark_record/.git/objects/07/e5b2a2750ff27d7277db2205cf2198d721d7c8
nonebot_ark_record/.git/objects/08/5445d476a416f67b8a4e294aeeffc281817be6
nonebot_ark_record/.git/objects/08/6a7c98f095d78888a6714afdb5035f3cd50617
nonebot_ark_record/.git/objects/09/46b7c5ad38f86bac995ce16fc48cf686fdcd6b
nonebot_ark_record/.git/objects/0d/d500dc81f0741970e7927a89432fa1251226da
nonebot_ark_record-1.0.2.dist-info/LICENSE
nonebot_ark_record-1.0.2.dist-info/WHEEL
nonebot_ark_record-1.0.2.dist-info/METADATA
nonebot_ark_record-1.0.2.dist-info/RECORD
